vqc/__init__.py
vqc/bench/__init__.py
vqc/bench/fidelity.py
vqc/circuit.py
vqc/converters.py
vqc/cut/__init__.py
vqc/cut/cut.py
vqc/cut/passes/__init__.py
vqc/cut/passes/approx.py
vqc/cut/passes/bisection.py
vqc/cut/passes/ladder.py
vqc/cut/passes/qubit_groups.py
vqc/cut/passes/static.py
vqc/device/__init__.py
vqc/device/device.py
vqc/device/ibmq.py
vqc/device/sim.py
vqc/executor/__init__.py
vqc/executor/executor.py
vqc/executor/frag_executor.py
vqc/executor/knit.py
vqc/prob.py
vqc/statistic.py
vqc/utils/__init__.py
vqc/utils/overhead.py
vqc/virtual_gate/__init__.py
vqc/virtual_gate/approx.py
vqc/virtual_gate/virtual_cx.py
vqc/virtual_gate/virtual_cz.py
vqc/virtual_gate/virtual_gate.py
vqc/virtual_gate/virtual_rzz.py
vqc-0.0.1.dist-info/LICENSE
vqc-0.0.1.dist-info/WHEEL
vqc-0.0.1.dist-info/METADATA
vqc-0.0.1.dist-info/RECORD
